brownie_metadata_db/__init__.py
brownie_metadata_db/certificates.py
brownie_metadata_db/backup/__init__.py
brownie_metadata_db/backup/cli.py
brownie_metadata_db/backup/config.py
brownie_metadata_db/backup/manager.py
brownie_metadata_db/backup/providers.py
brownie_metadata_db/backup/scheduler.py
brownie_metadata_db/certificates/__init__.py
brownie_metadata_db/certificates/config.py
brownie_metadata_db/certificates/validation.py
brownie_metadata_db/database/__init__.py
brownie_metadata_db/database/base.py
brownie_metadata_db/database/config.py
brownie_metadata_db/database/connection.py
brownie_metadata_db/database/models/__init__.py
brownie_metadata_db/database/models/agent_config.py
brownie_metadata_db/database/models/config.py
brownie_metadata_db/database/models/incident.py
brownie_metadata_db/database/models/organization.py
brownie_metadata_db/database/models/stats.py
brownie_metadata_db/database/models/team.py
brownie_metadata_db/database/models/user.py
brownie_metadata_db/logging/__init__.py
brownie_metadata_db/logging/audit.py
brownie_metadata_db/logging/config.py
brownie_metadata_db/logging/performance.py
brownie_metadata_db-0.1.0.dist-info/METADATA
brownie_metadata_db-0.1.0.dist-info/WHEEL
brownie_metadata_db-0.1.0.dist-info/entry_points.txt
brownie_metadata_db-0.1.0.dist-info/RECORD
