Metadata-Version: 2.4
Name: brownie-metadata-db
Version: 0.1.0
Summary: A comprehensive database management library for Brownie metadata with backup, SSL, and monitoring capabilities
Author-email: Your Name <your.email@example.com>
Keywords: backup,brownie,database,metadata,postgresql,ssl
Classifier: Development Status :: 4 - Beta
Classifier: Intended Audience :: Developers
Classifier: License :: OSI Approved :: MIT License
Classifier: Programming Language :: Python :: 3
Classifier: Programming Language :: Python :: 3.9
Classifier: Programming Language :: Python :: 3.10
Classifier: Programming Language :: Python :: 3.11
Classifier: Programming Language :: Python :: 3.12
Classifier: Topic :: Database
Classifier: Topic :: Software Development :: Libraries :: Python Modules
Requires-Python: >=3.9
Requires-Dist: alembic>=1.13.0
Requires-Dist: azure-storage-blob>=12.19.0
Requires-Dist: boto3>=1.34.0
Requires-Dist: click>=8.0.0
Requires-Dist: croniter>=2.0.0
Requires-Dist: google-cloud-storage>=2.10.0
Requires-Dist: prometheus-client>=0.19.0
Requires-Dist: psycopg2-binary>=2.9.0
Requires-Dist: psycopg[binary]>=3.2.1
Requires-Dist: pydantic-settings>=2.1.0
Requires-Dist: pydantic>=2.5.0
Requires-Dist: pyyaml>=6.0.0
Requires-Dist: redis>=5.0.1
Requires-Dist: schedule>=1.2.0
Requires-Dist: sqlalchemy>=2.0.23
Requires-Dist: structlog>=23.2.0
Provides-Extra: dev
Requires-Dist: black>=23.0.0; extra == 'dev'
Requires-Dist: isort>=5.12.0; extra == 'dev'
Requires-Dist: mypy>=1.7.0; extra == 'dev'
Requires-Dist: pre-commit>=3.5.0; extra == 'dev'
Requires-Dist: pytest-asyncio>=0.21.0; extra == 'dev'
Requires-Dist: pytest-cov>=4.1.0; extra == 'dev'
Requires-Dist: pytest-mock>=3.9.0; extra == 'dev'
Requires-Dist: pytest>=7.4.0; extra == 'dev'
Provides-Extra: vault
Requires-Dist: hvac>=1.0.0; extra == 'vault'
